{
  "workflow": "freeCodeCamp_freeCodeCamp__e2e-third-party.yml",
  "tools": {
    "frizbee": {
      "workflow": "freeCodeCamp_freeCodeCamp__e2e-third-party.yml",
      "tool": "frizbee",
      "summary": {
        "total_findings": 1,
        "by_rule": {
          "unpinned-github-actions": 1
        }
      },
      "findings": [
        {
          "rule": "unpinned-github-actions",
          "original": "actions/upload-artifact@v4",
          "pinned": "actions/upload-artifact@ea165f8d65b6e75b540449e92b4886f43607fa02",
          "line": 165,
          "capability": "pinning-check"
        }
      ]
    },
    "pinny": {
      "workflow": "freeCodeCamp_freeCodeCamp__e2e-third-party.yml",
      "tool": "pinny",
      "summary": {
        "total_findings": 12,
        "by_rule": {
          "unpinned-github-actions": 12
        }
      },
      "findings": [
        {
          "rule": "unpinned-github-actions",
          "pinned": "uses: actions/checkout@b4ffde65f46336ab88eb53be808477a3936bae11 # v4.1.1",
          "line": 19,
          "capability": "pinning-check"
        },
        {
          "rule": "unpinned-github-actions",
          "pinned": "uses: actions/checkout@b4ffde65f46336ab88eb53be808477a3936bae11 # v4.1.1",
          "line": 23,
          "capability": "pinning-check"
        },
        {
          "rule": "unpinned-github-actions",
          "pinned": "uses: pnpm/action-setup@a3252b78c470c02df07e9d59298aecedc3ccdd6d #v3.0.0",
          "line": 28,
          "capability": "pinning-check"
        },
        {
          "rule": "unpinned-github-actions",
          "pinned": "uses: actions/setup-node@60edb5dd545a775178f52524783378180af0d1f8 # v4.0.2",
          "line": 30,
          "capability": "pinning-check"
        },
        {
          "rule": "unpinned-github-actions",
          "pinned": "uses: actions/upload-artifact@5d5d22a31266ced268874388b861e4b58bb5c2f3 # v4.3.1",
          "line": 48,
          "capability": "pinning-check"
        },
        {
          "rule": "unpinned-github-actions",
          "pinned": "uses: actions/checkout@b4ffde65f46336ab88eb53be808477a3936bae11 # v4.1.1",
          "line": 57,
          "capability": "pinning-check"
        },
        {
          "rule": "unpinned-github-actions",
          "pinned": "uses: actions/upload-artifact@5d5d22a31266ced268874388b861e4b58bb5c2f3 # v4.3.1",
          "line": 68,
          "capability": "pinning-check"
        },
        {
          "rule": "unpinned-github-actions",
          "pinned": "uses: actions/checkout@b4ffde65f46336ab88eb53be808477a3936bae11 # v4.1.1",
          "line": 95,
          "capability": "pinning-check"
        },
        {
          "rule": "unpinned-github-actions",
          "pinned": "- uses: actions/download-artifact@c850b930e6ba138125429b7e5c93fc707a7f8427 # v4.1.4",
          "line": 96,
          "capability": "pinning-check"
        },
        {
          "rule": "unpinned-github-actions",
          "pinned": "uses: pnpm/action-setup@a3252b78c470c02df07e9d59298aecedc3ccdd6d #v3.0.0",
          "line": 106,
          "capability": "pinning-check"
        },
        {
          "rule": "unpinned-github-actions",
          "pinned": "uses: actions/setup-node@60edb5dd545a775178f52524783378180af0d1f8 # v4.0.2",
          "line": 108,
          "capability": "pinning-check"
        },
        {
          "rule": "unpinned-github-actions",
          "pinned": "- uses: actions/upload-artifact@ea165f8d65b6e75b540449e92b4886f43607fa02 # actions/upload-artifact@v4 | v4.6.2",
          "line": 135,
          "capability": "pinning-check"
        }
      ]
    },
    "scorecard": {
      "workflow": "freeCodeCamp_freeCodeCamp__e2e-third-party.yml",
      "tool": "scorecard",
      "summary": {
        "total_findings": 3,
        "by_rule": {
          "Pinned-Dependencies": 1,
          "SAST": 1,
          "Token-Permissions": 1
        }
      },
      "findings": [
        {
          "rule": "Pinned-Dependencies",
          "score": 9,
          "reason": "dependency not pinned by hash detected -- score normalized to 9",
          "lines": [
            165
          ],
          "raw_details": [
            "Warn: GitHub-owned GitHubAction not pinned by hash: .github/workflows/freeCodeCamp_freeCodeCamp__e2e-third-party.yml:165",
            "Info:   9 out of  10 GitHub-owned GitHubAction dependencies pinned",
            "Info:   2 out of   2 third-party GitHubAction dependencies pinned"
          ],
          "documentation": {
            "url": "https://github.com/ossf/scorecard/blob/ab2f6e92482462fe66246d9e32f642855a691dc1/docs/checks.md#pinned-dependencies",
            "short": "Determines if the project has declared and pinned the dependencies of its build process."
          },
          "capability": "pinning-check"
        },
        {
          "rule": "SAST",
          "score": 0,
          "reason": "no SAST tool detected",
          "lines": [],
          "raw_details": [
            "Warn: no pull requests merged into dev branch"
          ],
          "documentation": {
            "url": "https://github.com/ossf/scorecard/blob/ab2f6e92482462fe66246d9e32f642855a691dc1/docs/checks.md#sast",
            "short": "Determines if the project uses static code analysis."
          },
          "capability": "automatic-hardening-check"
        },
        {
          "rule": "Token-Permissions",
          "score": 0,
          "reason": "detected GitHub workflow tokens with excessive permissions",
          "lines": [
            1
          ],
          "raw_details": [
            "Warn: no topLevel permission defined: .github/workflows/freeCodeCamp_freeCodeCamp__e2e-third-party.yml:1",
            "Info: no jobLevel write permissions found"
          ],
          "documentation": {
            "url": "https://github.com/ossf/scorecard/blob/ab2f6e92482462fe66246d9e32f642855a691dc1/docs/checks.md#token-permissions",
            "short": "Determines if the project's workflows follow the principle of least privilege."
          },
          "capability": "permissions-check"
        }
      ]
    },
    "scharf": {
      "workflow": "freeCodeCamp_freeCodeCamp__e2e-third-party.yml",
      "tool": "scharf",
      "summary": {
        "total_findings": 1,
        "by_rule": {
          "unpinned-github-actions": 1
        }
      },
      "findings": [
        {
          "line": 165,
          "column": 15,
          "message": "Unpinned GitHub Action: uses `actions/upload-artifact@v4`",
          "capability": "pinning-check"
        }
      ]
    },
    "zizmor": {
      "workflow": "freeCodeCamp_freeCodeCamp__e2e-third-party.yml",
      "tool": "zizmor",
      "summary": {
        "total_findings": 9,
        "by_rule": {
          "artipacked": 4,
          "excessive-permissions": 4,
          "unpinned-images": 1
        }
      },
      "findings": [
        {
          "rule_id": "artipacked",
          "level": "warning",
          "message": "credential persistence through GitHub Actions artifacts",
          "workflow": "freeCodeCamp_freeCodeCamp__e2e-third-party.yml",
          "line": 21,
          "column": 9,
          "note": "audit confidence \u2192 Low",
          "capability": "artifact-Integrity-check"
        },
        {
          "rule_id": "artipacked",
          "level": "warning",
          "message": "credential persistence through GitHub Actions artifacts",
          "workflow": "freeCodeCamp_freeCodeCamp__e2e-third-party.yml",
          "line": 26,
          "column": 9,
          "note": "audit confidence \u2192 Low",
          "capability": "artifact-Integrity-check"
        },
        {
          "rule_id": "artipacked",
          "level": "warning",
          "message": "credential persistence through GitHub Actions artifacts",
          "workflow": "freeCodeCamp_freeCodeCamp__e2e-third-party.yml",
          "line": 68,
          "column": 9,
          "note": "audit confidence \u2192 Low",
          "capability": "artifact-Integrity-check"
        },
        {
          "rule_id": "artipacked",
          "level": "warning",
          "message": "credential persistence through GitHub Actions artifacts",
          "workflow": "freeCodeCamp_freeCodeCamp__e2e-third-party.yml",
          "line": 111,
          "column": 9,
          "note": "audit confidence \u2192 Low",
          "capability": "artifact-Integrity-check"
        },
        {
          "rule_id": "excessive-permissions",
          "level": "warning",
          "message": "overly broad permissions",
          "workflow": "freeCodeCamp_freeCodeCamp__e2e-third-party.yml",
          "line": 1,
          "column": 1,
          "note": "audit confidence \u2192 Medium",
          "capability": "permissions-check"
        },
        {
          "rule_id": "excessive-permissions",
          "level": "warning",
          "message": "overly broad permissions",
          "workflow": "freeCodeCamp_freeCodeCamp__e2e-third-party.yml",
          "line": 14,
          "column": 3,
          "note": "audit confidence \u2192 Medium",
          "capability": "permissions-check"
        },
        {
          "rule_id": "excessive-permissions",
          "level": "warning",
          "message": "overly broad permissions",
          "workflow": "freeCodeCamp_freeCodeCamp__e2e-third-party.yml",
          "line": 64,
          "column": 3,
          "note": "audit confidence \u2192 Medium",
          "capability": "permissions-check"
        },
        {
          "rule_id": "excessive-permissions",
          "level": "warning",
          "message": "overly broad permissions",
          "workflow": "freeCodeCamp_freeCodeCamp__e2e-third-party.yml",
          "line": 88,
          "column": 3,
          "note": "audit confidence \u2192 Medium",
          "capability": "permissions-check"
        },
        {
          "rule_id": "unpinned-images",
          "level": "error",
          "message": "unpinned image references",
          "workflow": "freeCodeCamp_freeCodeCamp__e2e-third-party.yml",
          "line": 103,
          "column": 9,
          "note": "audit confidence \u2192 High",
          "capability": "pinning-check"
        }
      ]
    }
  }
}