{
  "workflow": "facebook_react__shared_lint.yml",
  "tool": "zizmor",
  "summary": {
    "total_findings": 4,
    "by_rule": {
      "artipacked": 4
    }
  },
  "findings": [
    {
      "rule_id": "artipacked",
      "level": "warning",
      "message": "credential persistence through GitHub Actions artifacts",
      "workflow": "facebook_react__shared_lint.yml",
      "line": 24,
      "column": 9,
      "note": "audit confidence \u2192 Low"
    },
    {
      "rule_id": "artipacked",
      "level": "warning",
      "message": "credential persistence through GitHub Actions artifacts",
      "workflow": "facebook_react__shared_lint.yml",
      "line": 47,
      "column": 9,
      "note": "audit confidence \u2192 Low"
    },
    {
      "rule_id": "artipacked",
      "level": "warning",
      "message": "credential persistence through GitHub Actions artifacts",
      "workflow": "facebook_react__shared_lint.yml",
      "line": 70,
      "column": 9,
      "note": "audit confidence \u2192 Low"
    },
    {
      "rule_id": "artipacked",
      "level": "warning",
      "message": "credential persistence through GitHub Actions artifacts",
      "workflow": "facebook_react__shared_lint.yml",
      "line": 93,
      "column": 9,
      "note": "audit confidence \u2192 Low"
    }
  ]
}