{
  "workflow": "n8n-io_n8n__chromatic.yml",
  "tool": "zizmor",
  "summary": {
    "total_findings": 5,
    "by_rule": {
      "artipacked": 2,
      "excessive-permissions": 3
    }
  },
  "findings": [
    {
      "rule_id": "artipacked",
      "level": "warning",
      "message": "credential persistence through GitHub Actions artifacts",
      "workflow": "n8n-io_n8n__chromatic.yml",
      "line": 20,
      "column": 9,
      "note": "audit confidence \u2192 Low"
    },
    {
      "rule_id": "artipacked",
      "level": "warning",
      "message": "credential persistence through GitHub Actions artifacts",
      "workflow": "n8n-io_n8n__chromatic.yml",
      "line": 55,
      "column": 9,
      "note": "audit confidence \u2192 Low"
    },
    {
      "rule_id": "excessive-permissions",
      "level": "warning",
      "message": "overly broad permissions",
      "workflow": "n8n-io_n8n__chromatic.yml",
      "line": 1,
      "column": 1,
      "note": "audit confidence \u2192 Medium"
    },
    {
      "rule_id": "excessive-permissions",
      "level": "warning",
      "message": "overly broad permissions",
      "workflow": "n8n-io_n8n__chromatic.yml",
      "line": 15,
      "column": 3,
      "note": "audit confidence \u2192 Medium"
    },
    {
      "rule_id": "excessive-permissions",
      "level": "warning",
      "message": "overly broad permissions",
      "workflow": "n8n-io_n8n__chromatic.yml",
      "line": 43,
      "column": 3,
      "note": "audit confidence \u2192 Medium"
    }
  ]
}