{
  "workflow": "open-webui_open-webui__docker-build.yaml",
  "tool": "zizmor",
  "summary": {
    "total_findings": 53,
    "by_rule": {
      "artipacked": 4,
      "excessive-permissions": 5,
      "template-injection": 8,
      "unpinned-uses": 36
    }
  },
  "findings": [
    {
      "rule_id": "artipacked",
      "level": "warning",
      "message": "credential persistence through GitHub Actions artifacts",
      "workflow": "open-webui_open-webui__docker-build.yaml",
      "line": 45,
      "column": 9,
      "note": "audit confidence \u2192 Low"
    },
    {
      "rule_id": "artipacked",
      "level": "warning",
      "message": "credential persistence through GitHub Actions artifacts",
      "workflow": "open-webui_open-webui__docker-build.yaml",
      "line": 144,
      "column": 9,
      "note": "audit confidence \u2192 Low"
    },
    {
      "rule_id": "artipacked",
      "level": "warning",
      "message": "credential persistence through GitHub Actions artifacts",
      "workflow": "open-webui_open-webui__docker-build.yaml",
      "line": 246,
      "column": 9,
      "note": "audit confidence \u2192 Low"
    },
    {
      "rule_id": "artipacked",
      "level": "warning",
      "message": "credential persistence through GitHub Actions artifacts",
      "workflow": "open-webui_open-webui__docker-build.yaml",
      "line": 349,
      "column": 9,
      "note": "audit confidence \u2192 Low"
    },
    {
      "rule_id": "excessive-permissions",
      "level": "warning",
      "message": "overly broad permissions",
      "workflow": "open-webui_open-webui__docker-build.yaml",
      "line": 1,
      "column": 1,
      "note": "audit confidence \u2192 Medium"
    },
    {
      "rule_id": "excessive-permissions",
      "level": "warning",
      "message": "overly broad permissions",
      "workflow": "open-webui_open-webui__docker-build.yaml",
      "line": 422,
      "column": 3,
      "note": "audit confidence \u2192 Medium"
    },
    {
      "rule_id": "excessive-permissions",
      "level": "warning",
      "message": "overly broad permissions",
      "workflow": "open-webui_open-webui__docker-build.yaml",
      "line": 476,
      "column": 3,
      "note": "audit confidence \u2192 Medium"
    },
    {
      "rule_id": "excessive-permissions",
      "level": "warning",
      "message": "overly broad permissions",
      "workflow": "open-webui_open-webui__docker-build.yaml",
      "line": 532,
      "column": 3,
      "note": "audit confidence \u2192 Medium"
    },
    {
      "rule_id": "excessive-permissions",
      "level": "warning",
      "message": "overly broad permissions",
      "workflow": "open-webui_open-webui__docker-build.yaml",
      "line": 588,
      "column": 3,
      "note": "audit confidence \u2192 Medium"
    },
    {
      "rule_id": "template-injection",
      "level": "info",
      "message": "code injection via template expansion",
      "workflow": "open-webui_open-webui__docker-build.yaml",
      "line": 101,
      "column": 9,
      "note": "audit confidence \u2192 Low"
    },
    {
      "rule_id": "template-injection",
      "level": "info",
      "message": "code injection via template expansion",
      "workflow": "open-webui_open-webui__docker-build.yaml",
      "line": 203,
      "column": 9,
      "note": "audit confidence \u2192 Low"
    },
    {
      "rule_id": "template-injection",
      "level": "info",
      "message": "code injection via template expansion",
      "workflow": "open-webui_open-webui__docker-build.yaml",
      "line": 306,
      "column": 9,
      "note": "audit confidence \u2192 Low"
    },
    {
      "rule_id": "template-injection",
      "level": "info",
      "message": "code injection via template expansion",
      "workflow": "open-webui_open-webui__docker-build.yaml",
      "line": 408,
      "column": 9,
      "note": "audit confidence \u2192 Low"
    },
    {
      "rule_id": "template-injection",
      "level": "info",
      "message": "code injection via template expansion",
      "workflow": "open-webui_open-webui__docker-build.yaml",
      "line": 472,
      "column": 9,
      "note": "audit confidence \u2192 Low"
    },
    {
      "rule_id": "template-injection",
      "level": "info",
      "message": "code injection via template expansion",
      "workflow": "open-webui_open-webui__docker-build.yaml",
      "line": 528,
      "column": 9,
      "note": "audit confidence \u2192 Low"
    },
    {
      "rule_id": "template-injection",
      "level": "info",
      "message": "code injection via template expansion",
      "workflow": "open-webui_open-webui__docker-build.yaml",
      "line": 584,
      "column": 9,
      "note": "audit confidence \u2192 Low"
    },
    {
      "rule_id": "template-injection",
      "level": "info",
      "message": "code injection via template expansion",
      "workflow": "open-webui_open-webui__docker-build.yaml",
      "line": 640,
      "column": 9,
      "note": "audit confidence \u2192 Low"
    },
    {
      "rule_id": "unpinned-uses",
      "level": "error",
      "message": "unpinned action reference",
      "workflow": "open-webui_open-webui__docker-build.yaml",
      "line": 49,
      "column": 9,
      "note": "audit confidence \u2192 High"
    },
    {
      "rule_id": "unpinned-uses",
      "level": "error",
      "message": "unpinned action reference",
      "workflow": "open-webui_open-webui__docker-build.yaml",
      "line": 52,
      "column": 9,
      "note": "audit confidence \u2192 High"
    },
    {
      "rule_id": "unpinned-uses",
      "level": "error",
      "message": "unpinned action reference",
      "workflow": "open-webui_open-webui__docker-build.yaml",
      "line": 55,
      "column": 9,
      "note": "audit confidence \u2192 High"
    },
    {
      "rule_id": "unpinned-uses",
      "level": "error",
      "message": "unpinned action reference",
      "workflow": "open-webui_open-webui__docker-build.yaml",
      "line": 63,
      "column": 9,
      "note": "audit confidence \u2192 High"
    },
    {
      "rule_id": "unpinned-uses",
      "level": "error",
      "message": "unpinned action reference",
      "workflow": "open-webui_open-webui__docker-build.yaml",
      "line": 77,
      "column": 9,
      "note": "audit confidence \u2192 High"
    },
    {
      "rule_id": "unpinned-uses",
      "level": "error",
      "message": "unpinned action reference",
      "workflow": "open-webui_open-webui__docker-build.yaml",
      "line": 88,
      "column": 9,
      "note": "audit confidence \u2192 High"
    },
    {
      "rule_id": "unpinned-uses",
      "level": "error",
      "message": "unpinned action reference",
      "workflow": "open-webui_open-webui__docker-build.yaml",
      "line": 148,
      "column": 9,
      "note": "audit confidence \u2192 High"
    },
    {
      "rule_id": "unpinned-uses",
      "level": "error",
      "message": "unpinned action reference",
      "workflow": "open-webui_open-webui__docker-build.yaml",
      "line": 151,
      "column": 9,
      "note": "audit confidence \u2192 High"
    },
    {
      "rule_id": "unpinned-uses",
      "level": "error",
      "message": "unpinned action reference",
      "workflow": "open-webui_open-webui__docker-build.yaml",
      "line": 154,
      "column": 9,
      "note": "audit confidence \u2192 High"
    },
    {
      "rule_id": "unpinned-uses",
      "level": "error",
      "message": "unpinned action reference",
      "workflow": "open-webui_open-webui__docker-build.yaml",
      "line": 162,
      "column": 9,
      "note": "audit confidence \u2192 High"
    },
    {
      "rule_id": "unpinned-uses",
      "level": "error",
      "message": "unpinned action reference",
      "workflow": "open-webui_open-webui__docker-build.yaml",
      "line": 178,
      "column": 9,
      "note": "audit confidence \u2192 High"
    },
    {
      "rule_id": "unpinned-uses",
      "level": "error",
      "message": "unpinned action reference",
      "workflow": "open-webui_open-webui__docker-build.yaml",
      "line": 189,
      "column": 9,
      "note": "audit confidence \u2192 High"
    },
    {
      "rule_id": "unpinned-uses",
      "level": "error",
      "message": "unpinned action reference",
      "workflow": "open-webui_open-webui__docker-build.yaml",
      "line": 250,
      "column": 9,
      "note": "audit confidence \u2192 High"
    },
    {
      "rule_id": "unpinned-uses",
      "level": "error",
      "message": "unpinned action reference",
      "workflow": "open-webui_open-webui__docker-build.yaml",
      "line": 253,
      "column": 9,
      "note": "audit confidence \u2192 High"
    },
    {
      "rule_id": "unpinned-uses",
      "level": "error",
      "message": "unpinned action reference",
      "workflow": "open-webui_open-webui__docker-build.yaml",
      "line": 256,
      "column": 9,
      "note": "audit confidence \u2192 High"
    },
    {
      "rule_id": "unpinned-uses",
      "level": "error",
      "message": "unpinned action reference",
      "workflow": "open-webui_open-webui__docker-build.yaml",
      "line": 264,
      "column": 9,
      "note": "audit confidence \u2192 High"
    },
    {
      "rule_id": "unpinned-uses",
      "level": "error",
      "message": "unpinned action reference",
      "workflow": "open-webui_open-webui__docker-build.yaml",
      "line": 280,
      "column": 9,
      "note": "audit confidence \u2192 High"
    },
    {
      "rule_id": "unpinned-uses",
      "level": "error",
      "message": "unpinned action reference",
      "workflow": "open-webui_open-webui__docker-build.yaml",
      "line": 291,
      "column": 9,
      "note": "audit confidence \u2192 High"
    },
    {
      "rule_id": "unpinned-uses",
      "level": "error",
      "message": "unpinned action reference",
      "workflow": "open-webui_open-webui__docker-build.yaml",
      "line": 353,
      "column": 9,
      "note": "audit confidence \u2192 High"
    },
    {
      "rule_id": "unpinned-uses",
      "level": "error",
      "message": "unpinned action reference",
      "workflow": "open-webui_open-webui__docker-build.yaml",
      "line": 356,
      "column": 9,
      "note": "audit confidence \u2192 High"
    },
    {
      "rule_id": "unpinned-uses",
      "level": "error",
      "message": "unpinned action reference",
      "workflow": "open-webui_open-webui__docker-build.yaml",
      "line": 359,
      "column": 9,
      "note": "audit confidence \u2192 High"
    },
    {
      "rule_id": "unpinned-uses",
      "level": "error",
      "message": "unpinned action reference",
      "workflow": "open-webui_open-webui__docker-build.yaml",
      "line": 367,
      "column": 9,
      "note": "audit confidence \u2192 High"
    },
    {
      "rule_id": "unpinned-uses",
      "level": "error",
      "message": "unpinned action reference",
      "workflow": "open-webui_open-webui__docker-build.yaml",
      "line": 383,
      "column": 9,
      "note": "audit confidence \u2192 High"
    },
    {
      "rule_id": "unpinned-uses",
      "level": "error",
      "message": "unpinned action reference",
      "workflow": "open-webui_open-webui__docker-build.yaml",
      "line": 394,
      "column": 9,
      "note": "audit confidence \u2192 High"
    },
    {
      "rule_id": "unpinned-uses",
      "level": "error",
      "message": "unpinned action reference",
      "workflow": "open-webui_open-webui__docker-build.yaml",
      "line": 443,
      "column": 9,
      "note": "audit confidence \u2192 High"
    },
    {
      "rule_id": "unpinned-uses",
      "level": "error",
      "message": "unpinned action reference",
      "workflow": "open-webui_open-webui__docker-build.yaml",
      "line": 446,
      "column": 9,
      "note": "audit confidence \u2192 High"
    },
    {
      "rule_id": "unpinned-uses",
      "level": "error",
      "message": "unpinned action reference",
      "workflow": "open-webui_open-webui__docker-build.yaml",
      "line": 454,
      "column": 9,
      "note": "audit confidence \u2192 High"
    },
    {
      "rule_id": "unpinned-uses",
      "level": "error",
      "message": "unpinned action reference",
      "workflow": "open-webui_open-webui__docker-build.yaml",
      "line": 497,
      "column": 9,
      "note": "audit confidence \u2192 High"
    },
    {
      "rule_id": "unpinned-uses",
      "level": "error",
      "message": "unpinned action reference",
      "workflow": "open-webui_open-webui__docker-build.yaml",
      "line": 500,
      "column": 9,
      "note": "audit confidence \u2192 High"
    },
    {
      "rule_id": "unpinned-uses",
      "level": "error",
      "message": "unpinned action reference",
      "workflow": "open-webui_open-webui__docker-build.yaml",
      "line": 508,
      "column": 9,
      "note": "audit confidence \u2192 High"
    },
    {
      "rule_id": "unpinned-uses",
      "level": "error",
      "message": "unpinned action reference",
      "workflow": "open-webui_open-webui__docker-build.yaml",
      "line": 553,
      "column": 9,
      "note": "audit confidence \u2192 High"
    },
    {
      "rule_id": "unpinned-uses",
      "level": "error",
      "message": "unpinned action reference",
      "workflow": "open-webui_open-webui__docker-build.yaml",
      "line": 556,
      "column": 9,
      "note": "audit confidence \u2192 High"
    },
    {
      "rule_id": "unpinned-uses",
      "level": "error",
      "message": "unpinned action reference",
      "workflow": "open-webui_open-webui__docker-build.yaml",
      "line": 564,
      "column": 9,
      "note": "audit confidence \u2192 High"
    },
    {
      "rule_id": "unpinned-uses",
      "level": "error",
      "message": "unpinned action reference",
      "workflow": "open-webui_open-webui__docker-build.yaml",
      "line": 609,
      "column": 9,
      "note": "audit confidence \u2192 High"
    },
    {
      "rule_id": "unpinned-uses",
      "level": "error",
      "message": "unpinned action reference",
      "workflow": "open-webui_open-webui__docker-build.yaml",
      "line": 612,
      "column": 9,
      "note": "audit confidence \u2192 High"
    },
    {
      "rule_id": "unpinned-uses",
      "level": "error",
      "message": "unpinned action reference",
      "workflow": "open-webui_open-webui__docker-build.yaml",
      "line": 620,
      "column": 9,
      "note": "audit confidence \u2192 High"
    }
  ]
}