{
  "workflow": "excalidraw_excalidraw__autorelease-excalidraw.yml",
  "tool": "actionlint",
  "summary": {
    "total_findings": 2
  },
  "findings": [
    {
      "line": 12,
      "column": 15,
      "message": "the runner of \"actions/checkout@v2\" action is too old to run on GitHub Actions. update the action's version to fix this issue [action]"
    },
    {
      "line": 16,
      "column": 15,
      "message": "the runner of \"actions/setup-node@v2\" action is too old to run on GitHub Actions. update the action's version to fix this issue [action]"
    }
  ]
}